bitmex_websocket.py
main.py
util/__init__.py
util/api_key.py
bitmex_ws_onix-0.3.1.dist-info/METADATA
bitmex_ws_onix-0.3.1.dist-info/WHEEL
bitmex_ws_onix-0.3.1.dist-info/top_level.txt
bitmex_ws_onix-0.3.1.dist-info/RECORD
