Metadata-Version: 2.1
Name: bitmex-ws-onix
Version: 0.3.1
Summary: FoRK: Sample adapter for connecting to the BitMEX Websocket API.
Home-page: UNKNOWN
Author: Samuel Reed
Author-email: sam@bitmex.com
License: UNKNOWN
Platform: UNKNOWN
Requires-Dist: websocket-client (==0.53.0)
